README.rst
setup.py
hssa/AP.py
hssa/HS.py
hssa/HSFrame.py
hssa/HSSA.py
hssa/__init__.py
hssa/anisodiff.py
hssa.egg-info/PKG-INFO
hssa.egg-info/SOURCES.txt
hssa.egg-info/dependency_links.txt
hssa.egg-info/top_level.txt