Metadata-Version: 1.0
Name: hssa
Version: 0.4.1
Summary: Hyperspectral Segmentation Algorithm
Home-page: https://github.com/w4k2/ece
Author: Paweł Ksieniewicz
Author-email: pawel.ksieniewicz@pwr.edu.pl
License: GNU GENERAL PUBLIC LICENSE
